fixtures/__init__.py
fixtures/example.csv
fixtures/testcases.py
pytrendline/__init__.py
pytrendline/detect.py
pytrendline/plot.py
pytrendline/structs.py
pytrendline/util.py
pytrendline-1.0.1.dist-info/LICENSE
pytrendline-1.0.1.dist-info/METADATA
pytrendline-1.0.1.dist-info/WHEEL
pytrendline-1.0.1.dist-info/top_level.txt
pytrendline-1.0.1.dist-info/RECORD
